{
  "affected_components": [
    "BMS Thermal Control"
  ],
  "affected_files": [
    "src/bms/thermal_manager.c"
  ],
  "affected_requirements": [
    {
      "component": "BMS Thermal Control",
      "id": "BMS-REQ-112",
      "metadata": {},
      "metric": "max_cell_temp_c",
      "next_checks": [
        "BMS-HIL-FASTCHARGE-07"
      ],
      "operator": "<=",
      "requirement": "Maximum cell temperature during fast charging must not exceed 50 C",
      "safety_level": "high",
      "threshold": 50.0
    },
    {
      "component": "BMS Thermal Control",
      "id": "BMS-REQ-118",
      "metadata": {},
      "metric": "cooling_response_ms",
      "next_checks": [
        "BMS-HIL-FASTCHARGE-07"
      ],
      "operator": "<=",
      "requirement": "Cooling response delay during fast charging must not exceed 500 ms",
      "safety_level": "medium",
      "threshold": 500.0
    }
  ],
  "comparison_summary": {
    "introduced_failures": 0,
    "metric_deltas": 2,
    "missing_baseline": 0,
    "missing_current": 0,
    "preexisting_failures": 0,
    "resolved_failures": 0,
    "total_tests": 1,
    "unchanged_passes": 1
  },
  "confidence": "high",
  "confidence_factors": [
    "+ baseline_current_pair_present",
    "+ requirement_mapped",
    "+ affected_file_mapped"
  ],
  "confidence_score": 0.95,
  "evidence_summary": [
    "Verdict is successful change.",
    "Mapped affected files: src/bms/thermal_manager.c."
  ],
  "introduced_failures": [],
  "preexisting_failures": [],
  "recommended_next_checks": [
    "BMS-HIL-FASTCHARGE-07"
  ],
  "risk": "low",
  "risk_drivers": [
    "verdict:successful_change",
    "risk:low",
    "safety_level:high",
    "safety_level:medium",
    "threshold_passed:BMS-REQ-112:max_cell_temp_c",
    "threshold_passed:BMS-REQ-118:cooling_response_ms"
  ],
  "rules_triggered": [
    "R7_successful_covered_change"
  ],
  "schema_version": "avera.assessment.v0.2",
  "threshold_evidence": [
    {
      "baseline_passed": true,
      "baseline_value": 48.6,
      "current_passed": true,
      "current_value": 46.2,
      "metric": "max_cell_temp_c",
      "operator": "<=",
      "requirement_id": "BMS-REQ-112",
      "test_id": "BMS-SIL-FASTCHARGE-01",
      "threshold": 50.0
    },
    {
      "baseline_passed": true,
      "baseline_value": 455.0,
      "current_passed": true,
      "current_value": 390.0,
      "metric": "cooling_response_ms",
      "operator": "<=",
      "requirement_id": "BMS-REQ-118",
      "test_id": "BMS-SIL-FASTCHARGE-01",
      "threshold": 500.0
    }
  ],
  "verdict": "successful_change"
}
